pikz/__init__.py
pikz/compile.py
pikz-0.1.dist-info/LICENSE
pikz-0.1.dist-info/METADATA
pikz-0.1.dist-info/WHEEL
pikz-0.1.dist-info/top_level.txt
pikz-0.1.dist-info/RECORD
