Metadata-Version: 2.1
Name: pikz
Version: 0.1
Summary: A package to draw tikz pictures using Python
Home-page: https://github.com/KoenBaak/pikz
Author: Koen Baak
Author-email: koen.baak@hotmail.com
License: UNKNOWN
Platform: UNKNOWN
Classifier: Programming Language :: Python :: 3
Classifier: License :: OSI Approved :: MIT License
Classifier: Operating System :: OS Independent
Requires-Python: >=3.6
License-File: LICENSE
